{
    "data": [{
        "type": 1,
        "list_id": "1|149638975",
        "stick": 0,
        "stick_id": 0,
        "stick_start_at": 0,
        "stick_expire_at": 0,
        "stick_type": 0,
        "feed_source": "",
        "article": {
            "id": 149638975,
            "mask_id": "1wqr6kft",
            "uri": "meipian:\/\/article\/detail?__experimentIds__=&__feedType__=400014&__flush_num__=0&__locationId__=1&__path__=tag3&__trackId__=14b851ac93b322d0&mask_id=1wqr6kft&__showStyle__=3",
            "abstract": "　　春姑娘来了！我轻舒双臂柔情地把她搂进怀中，捻一丝春雨，赋一首情诗，怀着感恩的心，喜爱码字的情，款",
            "title": "【欢喜过大年】二月，让爱在春天绽放",
            "addition_user_id": 0,
            "addition": "",
            "addition_uri": "",
            "visit_count": 59784,
            "praise_count": 3149,
            "image_count": 13,
            "comment_count": 2962,
            "cover_imgs": ["http:\/\/static2.ivwen.com\/users\/13499984\/e4a2a6efe4544861ae5a8ea10f68bf03.jpg", "http:\/\/static2.ivwen.com\/users\/13499984\/0c5b37a194dd42f9bd84745d676a1cf8.jpg", "http:\/\/static2.ivwen.com\/users\/13499984\/1886068f6e6c4511937556958d200fc2.jpg"],
            "feed_tag_info": {
                "tag_name": "",
                "uri": ""
            },
            "addition_tag_info": {
                "tag_id": 0,
                "tag_name": "",
                "img_url": ""
            }
        },
        "video": {},
        "event": [],
        "author": {
            "id": 13499984,
            "uri": "meipian:\/\/user\/column?__experimentIds__=&__feedType__=400014&__flush_num__=0&__locationId__=1&__path__=tag3&__trackId__=14b851ac93b322d0&author_id=13499984",
            "is_official": 0,
            "nickname": "上善若水",
            "head_img": "http:\/\/static2.ivwen.com\/users\/13499984\/98f0278006af4b14acec930f96919ff4.jpg?meipian\/bucket\/ivwen\/key\/dXNlcnMvMTM0OTk5ODQvOThmMDI3ODAwNmFmNGIxNGFjZWM5MzBmOTY5MTlmZjQuanBn\/sign\/09a8f5aef8041b086fe74f2e22b97f8c",
            "bedge_img": "",
            "label_img": "",
            "tag_img": ""
        },
        "source": {
            "source": "feedV4"
        },
        "feed_type": 400014,
        "style": 3,
        "item_type": 1,
        "uninterest_option": [{
            "type": 1,
            "name": "不喜欢这篇文章",
            "target_id": "149638975"
        }, {
            "type": 2,
            "name": "不喜欢这个作者",
            "target_id": "13499984"
        }, {
            "type": 7,
            "name": "不喜欢这类文章",
            "target_id": ""
        }]
    }, {
        "type": 1,
        "list_id": "1|219470543",
        "stick": 0,
        "stick_id": 0,
        "stick_start_at": 0,
        "stick_expire_at": 0,
        "stick_type": 0,
        "feed_source": "",
        "article": {
            "id": 219470543,
            "mask_id": "2stn3fhn",
            "uri": "meipian:\/\/article\/detail?__experimentIds__=&__feedType__=400014&__flush_num__=0&__locationId__=2&__path__=tag3&__trackId__=14b851ac93b322d0&mask_id=2stn3fhn&__showStyle__=3",
            "abstract": "　　春满人间图片\/诗引\/诗心文苑和诗\/不老松继承古典诗词，把它发扬光大！\"明月松间照，清泉石上流”。",
            "title": "春满人间",
            "addition_user_id": 0,
            "addition": "",
            "addition_uri": "",
            "visit_count": 302,
            "praise_count": 25,
            "image_count": 28,
            "comment_count": 15,
            "cover_imgs": ["https:\/\/static2.ivwen.com\/users\/37065035\/9adfacb9182621488f2a44c983451278.jpg?imageMogr2\/crop\/!828x465a0a26", "https:\/\/static2.ivwen.com\/users\/37065035\/02d686ce71b2b8eda6dfa0839ce2c1ba.jpg?imageMogr2\/crop\/!640x360a0a33", "https:\/\/static2.ivwen.com\/users\/37065035\/e59e8eb7abe574b6284aa9c0371812a2.jpg?imageMogr2\/crop\/!900x506a0a46"],
            "feed_tag_info": {
                "tag_name": "精华推荐",
                "uri": "meipian:\/\/activity\/detail?__experimentIds__=&__feedType__=400014&__flush_num__=0&__locationId__=2&__maskId__=2stn3fhn&__path__=tag3&__trackId__=14b851ac93b322d0&topic_id=10"
            },
            "addition_tag_info": {
                "tag_id": 0,
                "tag_name": "",
                "img_url": ""
            }
        },
        "video": {},
        "event": [],
        "author": {
            "id": 37065035,
            "uri": "meipian:\/\/user\/column?__experimentIds__=&__feedType__=400014&__flush_num__=0&__locationId__=2&__path__=tag3&__trackId__=14b851ac93b322d0&author_id=37065035",
            "is_official": 0,
            "nickname": "不老松",
            "head_img": "https:\/\/ss2.meipian.me\/users\/37065035\/75e39636b1cb22f2a7eb7930bd427709",
            "bedge_img": "",
            "label_img": "",
            "tag_img": ""
        },
        "source": {
            "source": "feedV4"
        },
        "feed_type": 400014,
        "style": 3,
        "item_type": 1,
        "uninterest_option": [{
            "type": 1,
            "name": "不喜欢这篇文章",
            "target_id": "219470543"
        }, {
            "type": 2,
            "name": "不喜欢这个作者",
            "target_id": "37065035"
        }, {
            "type": 7,
            "name": "不喜欢这类文章",
            "target_id": ""
        }]
    }, {
        "type": 1,
        "list_id": "1|124424542",
        "stick": 0,
        "stick_id": 0,
        "stick_start_at": 0,
        "stick_expire_at": 0,
        "stick_type": 0,
        "feed_source": "",
        "article": {
            "id": 124424542,
            "mask_id": "1l5r5rr6",
            "uri": "meipian:\/\/article\/detail?__experimentIds__=&__feedType__=400014&__flush_num__=0&__locationId__=3&__path__=tag3&__trackId__=14b851ac93b322d0&mask_id=1l5r5rr6&__showStyle__=2",
            "abstract": "【唯美古风】　　片片飘红舞霓裳，芳菲易尽，红颜易老，这个秋天来的让人措手不及。眼波中流转着温柔，嘴角",
            "title": "问世间谁会为谁情深不移",
            "addition_user_id": 0,
            "addition": "",
            "addition_uri": "",
            "visit_count": 2302,
            "praise_count": 338,
            "image_count": 4,
            "comment_count": 181,
            "cover_imgs": ["http:\/\/static2.ivwen.com\/users\/7245093\/60bb86ec6050464d974b6c9d40f425f0.jpg?imageView2\/2\/w\/750\/h\/1400\/q\/80%7CimageMogr2\/crop\/!750x421.875a0a0", "http:\/\/static2.ivwen.com\/users\/7245093\/9defaa1dcbb54d849c399ee93036b00f.jpg?imageView2\/2\/w\/750\/h\/1400\/q\/80%7CimageMogr2\/crop\/!750x421.875a0a0", "http:\/\/static2.ivwen.com\/users\/7245093\/182ba929a4264b71ac83d4f56fa37ea8.jpg?imageView2\/2\/w\/750\/h\/1400\/q\/80%7CimageMogr2\/crop\/!750x421.875a0a0"],
            "feed_tag_info": {
                "tag_name": "",
                "uri": ""
            },
            "addition_tag_info": {
                "tag_id": 0,
                "tag_name": "",
                "img_url": ""
            }
        },
        "video": {},
        "event": [],
        "author": {
            "id": 7245093,
            "uri": "meipian:\/\/user\/column?__experimentIds__=&__feedType__=400014&__flush_num__=0&__locationId__=3&__path__=tag3&__trackId__=14b851ac93b322d0&author_id=7245093",
            "is_official": 0,
            "nickname": "青风 寂无声",
            "head_img": "http:\/\/static2.ivwen.com\/users\/7245093\/a2ef89d3d62b4fd9b0e2fc7d3506c422.jpg?meipian\/bucket\/ivwen\/key\/dXNlcnMvNzI0NTA5My9hMmVmODlkM2Q2MmI0ZmQ5YjBlMmZjN2QzNTA2YzQyMi5qcGc=\/sign\/7ed4783aebf906706195657d7b1e2300",
            "bedge_img": "",
            "label_img": "",
            "tag_img": ""
        },
        "source": {
            "source": "feedV4"
        },
        "feed_type": 400014,
        "style": 2,
        "item_type": 1,
        "uninterest_option": [{
            "type": 1,
            "name": "不喜欢这篇文章",
            "target_id": "124424542"
        }, {
            "type": 2,
            "name": "不喜欢这个作者",
            "target_id": "7245093"
        }, {
            "type": 7,
            "name": "不喜欢这类文章",
            "target_id": ""
        }]
    }, {
        "type": 1,
        "list_id": "1|221061562",
        "stick": 0,
        "stick_id": 0,
        "stick_start_at": 0,
        "stick_expire_at": 0,
        "stick_type": 0,
        "feed_source": "",
        "article": {
            "id": 221061562,
            "mask_id": "2tjycgx9",
            "uri": "meipian:\/\/article\/detail?__experimentIds__=&__feedType__=400014&__flush_num__=0&__locationId__=4&__path__=tag3&__trackId__=14b851ac93b322d0&mask_id=2tjycgx9&__showStyle__=9",
            "abstract": "哦，你的师你的母都走了，两个孽主，一个在牢房，一个在地狱，留下你，在村外冷水河桥哭。她来了，你的师，",
            "title": "哦，你的师你的母",
            "addition_user_id": 0,
            "addition": "",
            "addition_uri": "",
            "visit_count": 49,
            "praise_count": 28,
            "image_count": 2,
            "comment_count": 7,
            "cover_imgs": ["https:\/\/static2.ivwen.com\/users\/31412084\/a7b12cd613fc1fff845fcdc11d52b33a.jpg?imageMogr2\/crop\/!2000x1125a0a1113"],
            "feed_tag_info": {
                "tag_name": "精华推荐",
                "uri": "meipian:\/\/activity\/detail?__experimentIds__=&__feedType__=400014&__flush_num__=0&__locationId__=4&__maskId__=2tjycgx9&__path__=tag3&__trackId__=14b851ac93b322d0&topic_id=10"
            },
            "addition_tag_info": {
                "tag_id": 0,
                "tag_name": "",
                "img_url": ""
            }
        },
        "video": {},
        "event": [],
        "author": {
            "id": 31412084,
            "uri": "meipian:\/\/user\/column?__experimentIds__=&__feedType__=400014&__flush_num__=0&__locationId__=4&__path__=tag3&__trackId__=14b851ac93b322d0&author_id=31412084",
            "is_official": 0,
            "nickname": "悟空无",
            "head_img": "http:\/\/static2.ivwen.com\/users\/31412084\/869f1f2f60e94236909ee52b4f4baa1e.jpg?meipian\/bucket\/ivwen\/key\/dXNlcnMvMzE0MTIwODQvODY5ZjFmMmY2MGU5NDIzNjkwOWVlNTJiNGY0YmFhMWUuanBn\/sign\/7688943f2d3a8c6e9d20ccddd372715b",
            "bedge_img": "",
            "label_img": "",
            "tag_img": ""
        },
        "source": {
            "source": "feedV4"
        },
        "feed_type": 400014,
        "style": 9,
        "item_type": 1,
        "uninterest_option": [{
            "type": 1,
            "name": "不喜欢这篇文章",
            "target_id": "221061562"
        }, {
            "type": 2,
            "name": "不喜欢这个作者",
            "target_id": "31412084"
        }, {
            "type": 7,
            "name": "不喜欢这类文章",
            "target_id": ""
        }]
    }, {
        "type": 1,
        "list_id": "1|35219540",
        "stick": 0,
        "stick_id": 0,
        "stick_start_at": 0,
        "stick_expire_at": 0,
        "stick_type": 0,
        "feed_source": "",
        "article": {
            "id": 35219540,
            "mask_id": "g6gszbm",
            "uri": "meipian:\/\/article\/detail?__experimentIds__=&__feedType__=400014&__flush_num__=0&__locationId__=5&__path__=tag3&__trackId__=14b851ac93b322d0&mask_id=g6gszbm&__showStyle__=2",
            "abstract": "摄影：经典故事场地：广汉梨花沟 写一阕清词断章，于莲开的季节亦是浮生不老，初心不忘那些曾经青春年华",
            "title": "一念浅喜，一念深爱",
            "addition_user_id": 0,
            "addition": "",
            "addition_uri": "",
            "visit_count": 2899,
            "praise_count": 250,
            "image_count": 11,
            "comment_count": 65,
            "cover_imgs": ["http:\/\/static2.ivwen.com\/users\/2501081\/a1bc716ab79a45acb54e014e24f5cad3.jpg", "http:\/\/static2.ivwen.com\/users\/2501081\/a89751ec21ac44878045618cc25cc5ea.jpg?imageView2\/2\/w\/750\/h\/1400\/q\/80%7CimageMogr2\/crop\/!750x421.875a0a0", "http:\/\/static2.ivwen.com\/users\/2501081\/b4bd79cc5e88410aa1772549e4f7a8c6.jpg"],
            "feed_tag_info": {
                "tag_name": "",
                "uri": ""
            },
            "addition_tag_info": {
                "tag_id": 0,
                "tag_name": "",
                "img_url": ""
            }
        },
        "video": {},
        "event": [],
        "author": {
            "id": 2501081,
            "uri": "meipian:\/\/user\/column?__experimentIds__=&__feedType__=400014&__flush_num__=0&__locationId__=5&__path__=tag3&__trackId__=14b851ac93b322d0&author_id=2501081",
            "is_official": 0,
            "nickname": "浅浅笑",
            "head_img": "http:\/\/static2.ivwen.com\/users\/2501081\/defbe10039b64cb3978e2edf566b11e0.jpg?meipian\/bucket\/ivwen\/key\/dXNlcnMvMjUwMTA4MS9kZWZiZTEwMDM5YjY0Y2IzOTc4ZTJlZGY1NjZiMTFlMC5qcGc=\/sign\/e20ad3a5eca9dc5d2f87b57b30423971",
            "bedge_img": "",
            "label_img": "",
            "tag_img": ""
        },
        "source": {
            "source": "feedV4"
        },
        "feed_type": 400014,
        "style": 2,
        "item_type": 1,
        "uninterest_option": [{
            "type": 1,
            "name": "不喜欢这篇文章",
            "target_id": "35219540"
        }, {
            "type": 2,
            "name": "不喜欢这个作者",
            "target_id": "2501081"
        }, {
            "type": 7,
            "name": "不喜欢这类文章",
            "target_id": ""
        }]
    }, {
        "type": 1,
        "list_id": "1|211980325",
        "stick": 0,
        "stick_id": 0,
        "stick_start_at": 0,
        "stick_expire_at": 0,
        "stick_type": 0,
        "feed_source": "",
        "article": {
            "id": 211980325,
            "mask_id": "2pdrm2ba",
            "uri": "meipian:\/\/article\/detail?__experimentIds__=&__feedType__=400014&__flush_num__=0&__locationId__=6&__path__=tag3&__trackId__=14b851ac93b322d0&mask_id=2pdrm2ba&__showStyle__=3",
            "abstract": "作者：萍儿图片：萍儿我把满满的祝福&nbsp;珍藏于许愿树也许心从此不再孤独我把浓浓的情愫播撒在方寸",
            "title": "只要不认输，风雨过后就会赢得幸福",
            "addition_user_id": 0,
            "addition": "",
            "addition_uri": "",
            "visit_count": 955,
            "praise_count": 179,
            "image_count": 7,
            "comment_count": 126,
            "cover_imgs": ["https:\/\/static2.ivwen.com\/users\/246758\/42eb45230b4981f56edcea1d2b757414.jpg?imageMogr2\/crop\/!1079x607a0a482", "https:\/\/static2.ivwen.com\/users\/246758\/c42fd420507dc277e2a583f609267662.jpg?imageMogr2\/crop\/!1079x606a0a227", "https:\/\/static2.ivwen.com\/users\/246758\/4b11fb2fee2a2105b8a1ef80b58cb8ea.jpg?imageMogr2\/crop\/!1079x607a9a0"],
            "feed_tag_info": {
                "tag_name": "",
                "uri": ""
            },
            "addition_tag_info": {
                "tag_id": 0,
                "tag_name": "",
                "img_url": ""
            }
        },
        "video": {},
        "event": [],
        "author": {
            "id": 246758,
            "uri": "meipian:\/\/user\/column?__experimentIds__=&__feedType__=400014&__flush_num__=0&__locationId__=6&__path__=tag3&__trackId__=14b851ac93b322d0&author_id=246758",
            "is_official": 0,
            "nickname": "萍儿",
            "head_img": "http:\/\/static2.ivwen.com\/users\/246758\/0601baa312f34b269f4fb6e960530d7f.jpg?meipian\/bucket\/ivwen\/key\/dXNlcnMvMjQ2NzU4LzA2MDFiYWEzMTJmMzRiMjY5ZjRmYjZlOTYwNTMwZDdmLmpwZw==\/sign\/ef955149b7ad4e231a6de8d4d18f06a5",
            "bedge_img": "https:\/\/ss2.meipian.me\/app\/vip.png",
            "label_img": "https:\/\/ss2.meipian.me\/app\/label\/sign_mark2.png",
            "tag_img": ""
        },
        "source": {
            "source": "feedV4"
        },
        "feed_type": 400014,
        "style": 3,
        "item_type": 1,
        "uninterest_option": [{
            "type": 1,
            "name": "不喜欢这篇文章",
            "target_id": "211980325"
        }, {
            "type": 2,
            "name": "不喜欢这个作者",
            "target_id": "246758"
        }, {
            "type": 7,
            "name": "不喜欢这类文章",
            "target_id": ""
        }]
    }, {
        "type": 1,
        "list_id": "1|213323495",
        "stick": 0,
        "stick_id": 0,
        "stick_start_at": 0,
        "stick_expire_at": 0,
        "stick_type": 0,
        "feed_source": "",
        "article": {
            "id": 213323495,
            "mask_id": "2pzzau9p",
            "uri": "meipian:\/\/article\/detail?__experimentIds__=&__feedType__=400014&__flush_num__=0&__locationId__=7&__path__=tag3&__trackId__=14b851ac93b322d0&mask_id=2pzzau9p&__showStyle__=2",
            "abstract": "立春的含义2020年2月4日，17时3分，立春。又是一个新的轮回开启，也是我写《灯下闲语》开篇之作的",
            "title": "立春的含义及立春的诗情画意",
            "addition_user_id": 0,
            "addition": "",
            "addition_uri": "",
            "visit_count": 271,
            "praise_count": 87,
            "image_count": 25,
            "comment_count": 45,
            "cover_imgs": ["https:\/\/static2.ivwen.com\/users\/6627678\/c3bf0597f057df7e65357bced2a39b5c.jpg?imageMogr2\/crop\/!821x461a1a1", "https:\/\/static2.ivwen.com\/users\/6627678\/8d6478b6f6ae032f56d2a61e4e129646.jpg?imageMogr2\/crop\/!1600x900a0a82", "https:\/\/static2.ivwen.com\/users\/6627678\/07fcfc2d266a1a0daabdeb660ce4611d.jpg?imageMogr2\/crop\/!1080x607a0a26"],
            "feed_tag_info": {
                "tag_name": "精华推荐",
                "uri": "meipian:\/\/activity\/detail?__experimentIds__=&__feedType__=400014&__flush_num__=0&__locationId__=7&__maskId__=2pzzau9p&__path__=tag3&__trackId__=14b851ac93b322d0&topic_id=10"
            },
            "addition_tag_info": {
                "tag_id": 0,
                "tag_name": "",
                "img_url": ""
            }
        },
        "video": {},
        "event": [],
        "author": {
            "id": 6627678,
            "uri": "meipian:\/\/user\/column?__experimentIds__=&__feedType__=400014&__flush_num__=0&__locationId__=7&__path__=tag3&__trackId__=14b851ac93b322d0&author_id=6627678",
            "is_official": 0,
            "nickname": "铁骨柔情(谭跃建)",
            "head_img": "https:\/\/ss2.meipian.me\/users\/6627678\/cd9c2428eb324d6595b9b0f357ec3609.jpg",
            "bedge_img": "",
            "label_img": "",
            "tag_img": ""
        },
        "source": {
            "source": "feedV4"
        },
        "feed_type": 400014,
        "style": 2,
        "item_type": 1,
        "uninterest_option": [{
            "type": 1,
            "name": "不喜欢这篇文章",
            "target_id": "213323495"
        }, {
            "type": 2,
            "name": "不喜欢这个作者",
            "target_id": "6627678"
        }, {
            "type": 7,
            "name": "不喜欢这类文章",
            "target_id": ""
        }]
    }, {
        "type": 1,
        "list_id": "1|200593979",
        "stick": 0,
        "stick_id": 0,
        "stick_start_at": 0,
        "stick_expire_at": 0,
        "stick_type": 0,
        "feed_source": "",
        "article": {
            "id": 200593979,
            "mask_id": "2k5gh5br",
            "uri": "meipian:\/\/article\/detail?__experimentIds__=&__feedType__=400014&__flush_num__=0&__locationId__=8&__path__=tag3&__trackId__=14b851ac93b322d0&mask_id=2k5gh5br&__showStyle__=3",
            "abstract": "文字：爱心永恒朗诵：苏堤\/听雨摄影：我心依然出镜：笑笑时光悠悠，尘烟朦朦，故事没有落脚，在时针与分针",
            "title": "梅雪情缘",
            "addition_user_id": 0,
            "addition": "",
            "addition_uri": "",
            "visit_count": 1067,
            "praise_count": 314,
            "image_count": 17,
            "comment_count": 157,
            "cover_imgs": ["https:\/\/static2.ivwen.com\/users\/11770256\/87c27409ffc843c7aac67570b7bfb148.jpg?imageMogr2\/crop\/!957x538a4a35", "http:\/\/static2.ivwen.com\/users\/11770256\/db87d3cb9d9a7b041b0e817fb0174a94.jpg", "http:\/\/static2.ivwen.com\/users\/11770256\/b348858fd27141bda821d2f9e9157f0c.jpg"],
            "feed_tag_info": {
                "tag_name": "",
                "uri": ""
            },
            "addition_tag_info": {
                "tag_id": 0,
                "tag_name": "",
                "img_url": ""
            }
        },
        "video": {},
        "event": [],
        "author": {
            "id": 11770256,
            "uri": "meipian:\/\/user\/column?__experimentIds__=&__feedType__=400014&__flush_num__=0&__locationId__=8&__path__=tag3&__trackId__=14b851ac93b322d0&author_id=11770256",
            "is_official": 0,
            "nickname": "爱心永恒",
            "head_img": "https:\/\/ss2.meipian.me\/users\/11770256\/6a58550f44cd4e719841d94f31178c29.jpg",
            "bedge_img": "",
            "label_img": "",
            "tag_img": ""
        },
        "source": {
            "source": "feedV4"
        },
        "feed_type": 400014,
        "style": 3,
        "item_type": 1,
        "uninterest_option": [{
            "type": 1,
            "name": "不喜欢这篇文章",
            "target_id": "200593979"
        }, {
            "type": 2,
            "name": "不喜欢这个作者",
            "target_id": "11770256"
        }, {
            "type": 7,
            "name": "不喜欢这类文章",
            "target_id": ""
        }]
    }, {
        "type": 1,
        "list_id": "1|217272137",
        "stick": 0,
        "stick_id": 0,
        "stick_start_at": 0,
        "stick_expire_at": 0,
        "stick_type": 0,
        "feed_source": "",
        "article": {
            "id": 217272137,
            "mask_id": "2rta7yl0",
            "uri": "meipian:\/\/article\/detail?__experimentIds__=&__feedType__=400014&__flush_num__=0&__locationId__=9&__path__=tag3&__trackId__=14b851ac93b322d0&mask_id=2rta7yl0&__showStyle__=2",
            "abstract": "春天遐思文字原创／布衣杨奇／抗疫日记清晨一缕阳光透过窗户；房间洒满热烈，洒满温度。我轻轻推开窗，啊，",
            "title": "春天遐思",
            "addition_user_id": 0,
            "addition": "",
            "addition_uri": "",
            "visit_count": 75,
            "praise_count": 18,
            "image_count": 3,
            "comment_count": 25,
            "cover_imgs": ["https:\/\/static2.ivwen.com\/users\/70448460\/fb1e3a617ca01529768919639365a2e5.jpg?imageMogr2\/crop\/!940x529a55a593", "http:\/\/static2.ivwen.com\/users\/70448460\/3f5a5bddd5306e95301c21f7e2c86d54.jpg", "http:\/\/static2.ivwen.com\/users\/70448460\/c499cdcc6e2ac7ea42b5d6e694d5bee5.jpg"],
            "feed_tag_info": {
                "tag_name": "朗诵吧，读读你爱的文字",
                "uri": "meipian:\/\/activity\/detail?__experimentIds__=&__feedType__=400014&__flush_num__=0&__locationId__=9&__maskId__=2rta7yl0&__path__=tag3&__trackId__=14b851ac93b322d0&topic_id=126"
            },
            "addition_tag_info": {
                "tag_id": 0,
                "tag_name": "",
                "img_url": ""
            }
        },
        "video": {},
        "event": [],
        "author": {
            "id": 70448460,
            "uri": "meipian:\/\/user\/column?__experimentIds__=&__feedType__=400014&__flush_num__=0&__locationId__=9&__path__=tag3&__trackId__=14b851ac93b322d0&author_id=70448460",
            "is_official": 0,
            "nickname": "布衣杨奇",
            "head_img": "https:\/\/ss2.meipian.me\/users\/70448460\/602d6291b680a87c4b9ef896d47682d5",
            "bedge_img": "",
            "label_img": "",
            "tag_img": ""
        },
        "source": {
            "source": "feedV4"
        },
        "feed_type": 400014,
        "style": 2,
        "item_type": 1,
        "uninterest_option": [{
            "type": 1,
            "name": "不喜欢这篇文章",
            "target_id": "217272137"
        }, {
            "type": 2,
            "name": "不喜欢这个作者",
            "target_id": "70448460"
        }, {
            "type": 7,
            "name": "不喜欢这类文章",
            "target_id": ""
        }]
    }, {
        "type": 1,
        "list_id": "1|214967159",
        "stick": 0,
        "stick_id": 0,
        "stick_start_at": 0,
        "stick_expire_at": 0,
        "stick_type": 0,
        "feed_source": "",
        "article": {
            "id": 214967159,
            "mask_id": "2qr5w9y9",
            "uri": "meipian:\/\/article\/detail?__experimentIds__=&__feedType__=400014&__flush_num__=0&__locationId__=10&__path__=tag3&__trackId__=14b851ac93b322d0&mask_id=2qr5w9y9&__showStyle__=3",
            "abstract": "没有冬天不可逾越，没有春天不会到来。一场疫情，让我们无所适从无比沮丧，原来看似再平常不过的小事，现在",
            "title": "等疫情过去，带上一份好的心情，打开门出去走走",
            "addition_user_id": 0,
            "addition": "",
            "addition_uri": "",
            "visit_count": 112,
            "praise_count": 8,
            "image_count": 53,
            "comment_count": 2,
            "cover_imgs": ["https:\/\/static2.ivwen.com\/users\/3619875\/4fbadb225a311c56ebf1e7910a1bc07b.jpg?imageMogr2\/crop\/!2160x1215a0a19", "https:\/\/static2.ivwen.com\/users\/3619875\/bcaec748e3e4581da44df4e063b7a4b3.jpg?imageMogr2\/crop\/!2997x1685a0a157", "https:\/\/static2.ivwen.com\/users\/3619875\/bc3f4e95473a68057ad66063ae8ed96e.jpg?imageMogr2\/crop\/!2160x1215a0a186"],
            "feed_tag_info": {
                "tag_name": "晒晒我爱的那些花",
                "uri": "meipian:\/\/activity\/detail?__experimentIds__=&__feedType__=400014&__flush_num__=0&__locationId__=10&__maskId__=2qr5w9y9&__path__=tag3&__trackId__=14b851ac93b322d0&topic_id=51"
            },
            "addition_tag_info": {
                "tag_id": 0,
                "tag_name": "",
                "img_url": ""
            }
        },
        "video": {},
        "event": [],
        "author": {
            "id": 3619875,
            "uri": "meipian:\/\/user\/column?__experimentIds__=&__feedType__=400014&__flush_num__=0&__locationId__=10&__path__=tag3&__trackId__=14b851ac93b322d0&author_id=3619875",
            "is_official": 0,
            "nickname": "静",
            "head_img": "https:\/\/ss2.meipian.me\/users\/3619875\/dc339605346b44ca9a3a48b636da855a.jpg",
            "bedge_img": "",
            "label_img": "",
            "tag_img": ""
        },
        "source": {
            "source": "feedV4"
        },
        "feed_type": 400014,
        "style": 3,
        "item_type": 1,
        "uninterest_option": [{
            "type": 1,
            "name": "不喜欢这篇文章",
            "target_id": "214967159"
        }, {
            "type": 2,
            "name": "不喜欢这个作者",
            "target_id": "3619875"
        }, {
            "type": 7,
            "name": "不喜欢这类文章",
            "target_id": ""
        }]
    }, {
        "type": 1,
        "list_id": "1|213966032",
        "stick": 0,
        "stick_id": 0,
        "stick_start_at": 0,
        "stick_expire_at": 0,
        "stick_type": 0,
        "feed_source": "",
        "article": {
            "id": 213966032,
            "mask_id": "2qalun2d",
            "uri": "meipian:\/\/article\/detail?__experimentIds__=&__feedType__=400014&__flush_num__=0&__locationId__=11&__path__=tag3&__trackId__=14b851ac93b322d0&mask_id=2qalun2d&__showStyle__=3",
            "abstract": "【闲情】（新韵）今日寒捎雨水来，小炉烧水泡茶开。泛黄书卷贤人著，精妙绝伦手掌拍。【七绝·梅香】风寒孤",
            "title": "今日寒捎雨水来，小炉烧水泡茶开",
            "addition_user_id": 0,
            "addition": "",
            "addition_uri": "",
            "visit_count": 197,
            "praise_count": 84,
            "image_count": 11,
            "comment_count": 66,
            "cover_imgs": ["https:\/\/static2.ivwen.com\/users\/73183626\/72aadd031f7d72fb66cff0158dfcf315.jpg?imageMogr2\/crop\/!2667x1500a0a249", "https:\/\/static2.ivwen.com\/users\/73183626\/16f051bbb8d4a8fc45aa14ca23a4bf09.jpg?imageMogr2\/crop\/!800x450a1a9", "https:\/\/static2.ivwen.com\/users\/73183626\/2f841730c0c6a183022ebe78d34118ba.jpg?imageMogr2\/crop\/!1440x810a0a135"],
            "feed_tag_info": {
                "tag_name": "我的原创诗",
                "uri": "meipian:\/\/activity\/detail?__experimentIds__=&__feedType__=400014&__flush_num__=0&__locationId__=11&__maskId__=2qalun2d&__path__=tag3&__trackId__=14b851ac93b322d0&topic_id=52"
            },
            "addition_tag_info": {
                "tag_id": 0,
                "tag_name": "",
                "img_url": ""
            }
        },
        "video": {},
        "event": [],
        "author": {
            "id": 73183626,
            "uri": "meipian:\/\/user\/column?__experimentIds__=&__feedType__=400014&__flush_num__=0&__locationId__=11&__path__=tag3&__trackId__=14b851ac93b322d0&author_id=73183626",
            "is_official": 0,
            "nickname": "青峰",
            "head_img": "https:\/\/ss2.meipian.me\/users\/73183626\/09485f9245104e74921aae11b1b4dcb3.jpg",
            "bedge_img": "",
            "label_img": "",
            "tag_img": ""
        },
        "source": {
            "source": "feedV4"
        },
        "feed_type": 400014,
        "style": 3,
        "item_type": 1,
        "uninterest_option": [{
            "type": 1,
            "name": "不喜欢这篇文章",
            "target_id": "213966032"
        }, {
            "type": 2,
            "name": "不喜欢这个作者",
            "target_id": "73183626"
        }, {
            "type": 7,
            "name": "不喜欢这类文章",
            "target_id": ""
        }]
    }, {
        "type": 1,
        "list_id": "1|206947871",
        "stick": 0,
        "stick_id": 0,
        "stick_start_at": 0,
        "stick_expire_at": 0,
        "stick_type": 0,
        "feed_source": "",
        "article": {
            "id": 206947871,
            "mask_id": "2n2jf3f2",
            "uri": "meipian:\/\/article\/detail?__experimentIds__=&__feedType__=400014&__flush_num__=0&__locationId__=12&__path__=tag3&__trackId__=14b851ac93b322d0&mask_id=2n2jf3f2&__showStyle__=2",
            "abstract": "文字\/素笺淡墨图片\/网络配图冬丝丝寒意清凉了几许冷了容颜凉了眉梢天空该是飘着片片雪绒白羽以静幽之姿恬",
            "title": "书一腔柔情，盼一场落雪",
            "addition_user_id": 0,
            "addition": "",
            "addition_uri": "",
            "visit_count": 776,
            "praise_count": 153,
            "image_count": 8,
            "comment_count": 61,
            "cover_imgs": ["https:\/\/static2.ivwen.com\/users\/36989154\/143b01838d42f0e7dadc755fd533e46a.jpg?imageMogr2\/crop\/!1000x562a0a18", "http:\/\/static2.ivwen.com\/users\/36989154\/92e6b95925c6a7516fd6b9748ff35a85.jpg", "http:\/\/static2.ivwen.com\/users\/36989154\/24b4a698535f1d80f31036d6d50f2be6.jpg"],
            "feed_tag_info": {
                "tag_name": "精华推荐",
                "uri": "meipian:\/\/activity\/detail?__experimentIds__=&__feedType__=400014&__flush_num__=0&__locationId__=12&__maskId__=2n2jf3f2&__path__=tag3&__trackId__=14b851ac93b322d0&topic_id=10"
            },
            "addition_tag_info": {
                "tag_id": 0,
                "tag_name": "",
                "img_url": ""
            }
        },
        "video": {},
        "event": [],
        "author": {
            "id": 36989154,
            "uri": "meipian:\/\/user\/column?__experimentIds__=&__feedType__=400014&__flush_num__=0&__locationId__=12&__path__=tag3&__trackId__=14b851ac93b322d0&author_id=36989154",
            "is_official": 0,
            "nickname": "素笺淡墨",
            "head_img": "https:\/\/ss2.meipian.me\/users\/36989154\/71160e48208440e7ac40414b89ac57b4.jpg",
            "bedge_img": "",
            "label_img": "",
            "tag_img": ""
        },
        "source": {
            "source": "feedV4"
        },
        "feed_type": 400014,
        "style": 2,
        "item_type": 1,
        "uninterest_option": [{
            "type": 1,
            "name": "不喜欢这篇文章",
            "target_id": "206947871"
        }, {
            "type": 2,
            "name": "不喜欢这个作者",
            "target_id": "36989154"
        }, {
            "type": 7,
            "name": "不喜欢这类文章",
            "target_id": ""
        }]
    }, {
        "type": 1,
        "list_id": "1|128547001",
        "stick": 0,
        "stick_id": 0,
        "stick_start_at": 0,
        "stick_expire_at": 0,
        "stick_type": 0,
        "feed_source": "",
        "article": {
            "id": 128547001,
            "mask_id": "1n1xkcsl",
            "uri": "meipian:\/\/article\/detail?__experimentIds__=&__feedType__=400014&__flush_num__=0&__locationId__=13&__path__=tag3&__trackId__=14b851ac93b322d0&mask_id=1n1xkcsl&__showStyle__=3",
            "abstract": "文字：清凝配图：来源于网络配乐：《我爱你，中国》前言：十月的天空，流光溢彩，十月的大地，笑语欢歌。在",
            "title": "有一种表白，叫《我爱你，中国》",
            "addition_user_id": 0,
            "addition": "",
            "addition_uri": "",
            "visit_count": 17368,
            "praise_count": 2176,
            "image_count": 6,
            "comment_count": 179,
            "cover_imgs": ["http:\/\/static2.ivwen.com\/users\/10570588\/ee01b568ef394340a58693903a090f61.jpg", "http:\/\/static2.ivwen.com\/users\/10570588\/498d6aaf26a1460d831227c4d376a07b.jpg", "http:\/\/static2.ivwen.com\/users\/10570588\/75c6fc6128aa4e73aa70e10cf7779bf0.jpg"],
            "feed_tag_info": {
                "tag_name": "",
                "uri": ""
            },
            "addition_tag_info": {
                "tag_id": 0,
                "tag_name": "",
                "img_url": ""
            }
        },
        "video": {},
        "event": [],
        "author": {
            "id": 10570588,
            "uri": "meipian:\/\/user\/column?__experimentIds__=&__feedType__=400014&__flush_num__=0&__locationId__=13&__path__=tag3&__trackId__=14b851ac93b322d0&author_id=10570588",
            "is_official": 0,
            "nickname": "清凝",
            "head_img": "https:\/\/ss2.meipian.me\/users\/10570588\/d0f704614ef24a0986730d5ce11d62fc.jpg",
            "bedge_img": "",
            "label_img": "",
            "tag_img": ""
        },
        "source": {
            "source": "feedV4"
        },
        "feed_type": 400014,
        "style": 3,
        "item_type": 1,
        "uninterest_option": [{
            "type": 1,
            "name": "不喜欢这篇文章",
            "target_id": "128547001"
        }, {
            "type": 2,
            "name": "不喜欢这个作者",
            "target_id": "10570588"
        }, {
            "type": 7,
            "name": "不喜欢这类文章",
            "target_id": ""
        }]
    }, {
        "type": 1,
        "list_id": "1|218894464",
        "stick": 0,
        "stick_id": 0,
        "stick_start_at": 0,
        "stick_expire_at": 0,
        "stick_type": 0,
        "feed_source": "",
        "article": {
            "id": 218894464,
            "mask_id": "2sk441sz",
            "uri": "meipian:\/\/article\/detail?__experimentIds__=&__feedType__=400014&__flush_num__=0&__locationId__=14&__path__=tag3&__trackId__=14b851ac93b322d0&mask_id=2sk441sz&__showStyle__=2",
            "abstract": "故乡滋味凸凹　　编者荐语：这是一篇触动人心的散文，凸凹先生以他自然真挚的笔墨，回忆了他去故乡时的感受",
            "title": "阅读推荐：《故乡滋味》",
            "addition_user_id": 0,
            "addition": "",
            "addition_uri": "",
            "visit_count": 127,
            "praise_count": 17,
            "image_count": 5,
            "comment_count": 7,
            "cover_imgs": ["https:\/\/static2.ivwen.com\/users\/15421917\/0629d1f07d47499caa66ddd830914666.jpeg?imageMogr2\/crop\/!260x146a0a32", "http:\/\/static2.ivwen.com\/users\/15421917\/19944485f1274b6c90fed0a30fa85b60.jpeg", "http:\/\/static2.ivwen.com\/users\/15421917\/1a6a12abc31644359a4f8889c3499d1c.jpeg?imageView2\/2\/w\/750\/h\/1400\/q\/80%7CimageMogr2\/crop\/!499x280.6875a0a0"],
            "feed_tag_info": {
                "tag_name": "",
                "uri": ""
            },
            "addition_tag_info": {
                "tag_id": 0,
                "tag_name": "",
                "img_url": ""
            }
        },
        "video": {},
        "event": [],
        "author": {
            "id": 15421917,
            "uri": "meipian:\/\/user\/column?__experimentIds__=&__feedType__=400014&__flush_num__=0&__locationId__=14&__path__=tag3&__trackId__=14b851ac93b322d0&author_id=15421917",
            "is_official": 0,
            "nickname": "穆启春",
            "head_img": "http:\/\/static2.ivwen.com\/users\/15421917\/d22df660d70f423f92e4fab59106cbf2.jpg?meipian\/bucket\/ivwen\/key\/dXNlcnMvMTU0MjE5MTcvZDIyZGY2NjBkNzBmNDIzZjkyZTRmYWI1OTEwNmNiZjIuanBn\/sign\/428bd9ffbfb8d1a571e4824365351829",
            "bedge_img": "",
            "label_img": "",
            "tag_img": ""
        },
        "source": {
            "source": "feedV4"
        },
        "feed_type": 400014,
        "style": 2,
        "item_type": 1,
        "uninterest_option": [{
            "type": 1,
            "name": "不喜欢这篇文章",
            "target_id": "218894464"
        }, {
            "type": 2,
            "name": "不喜欢这个作者",
            "target_id": "15421917"
        }, {
            "type": 7,
            "name": "不喜欢这类文章",
            "target_id": ""
        }]
    }, {
        "type": 1,
        "list_id": "1|124248650",
        "stick": 0,
        "stick_id": 0,
        "stick_start_at": 0,
        "stick_expire_at": 0,
        "stick_type": 0,
        "feed_source": "",
        "article": {
            "id": 124248650,
            "mask_id": "1l2ufsf2",
            "uri": "meipian:\/\/article\/detail?__experimentIds__=&__feedType__=400014&__flush_num__=0&__locationId__=15&__path__=tag3&__trackId__=14b851ac93b322d0&mask_id=1l2ufsf2&__showStyle__=3",
            "abstract": "说到四大美女，大家都会不约而同地想到闭月羞花沉鱼落雁，这四个人是花容月貌的代名词，是千百年来美女的统",
            "title": "天生就有魅惑之功，她的绯闻都上了《诗经》！",
            "addition_user_id": 0,
            "addition": "",
            "addition_uri": "",
            "visit_count": 5085,
            "praise_count": 148,
            "image_count": 5,
            "comment_count": 17,
            "cover_imgs": ["http:\/\/static2.ivwen.com\/users\/14410225\/157404d5677246ccbb8dad503f7790ae.jpg?imageView2\/2\/w\/750\/h\/1400\/q\/80%7CimageMogr2\/crop\/!500x281.25a0a0", "http:\/\/static2.ivwen.com\/users\/14410225\/b1167e3bd18b44d7bd754352939667d0.jpg", "http:\/\/static2.ivwen.com\/users\/14410225\/35a95df417c246958cc67af2c38019e5.jpg?imageView2\/2\/w\/750\/h\/1400\/q\/80%7CimageMogr2\/crop\/!675x379.6875a0a0"],
            "feed_tag_info": {
                "tag_name": "精华推荐",
                "uri": "meipian:\/\/activity\/detail?__experimentIds__=&__feedType__=400014&__flush_num__=0&__locationId__=15&__maskId__=1l2ufsf2&__path__=tag3&__trackId__=14b851ac93b322d0&topic_id=10"
            },
            "addition_tag_info": {
                "tag_id": 0,
                "tag_name": "",
                "img_url": ""
            }
        },
        "video": {},
        "event": [],
        "author": {
            "id": 14410225,
            "uri": "meipian:\/\/user\/column?__experimentIds__=&__feedType__=400014&__flush_num__=0&__locationId__=15&__path__=tag3&__trackId__=14b851ac93b322d0&author_id=14410225",
            "is_official": 0,
            "nickname": "打起黄雀儿",
            "head_img": "https:\/\/ss2.meipian.me\/users\/14410225\/4820c2ff14c74196a2e58668d7d26cc7.jpg",
            "bedge_img": "https:\/\/ss2.meipian.me\/app\/vip.png",
            "label_img": "https:\/\/ss2.meipian.me\/app\/label\/sign_mark2.png",
            "tag_img": ""
        },
        "source": {
            "source": "feedV4"
        },
        "feed_type": 400014,
        "style": 3,
        "item_type": 1,
        "uninterest_option": [{
            "type": 1,
            "name": "不喜欢这篇文章",
            "target_id": "124248650"
        }, {
            "type": 2,
            "name": "不喜欢这个作者",
            "target_id": "14410225"
        }, {
            "type": 7,
            "name": "不喜欢这类文章",
            "target_id": ""
        }]
    }, {
        "type": 1,
        "list_id": "1|156261927",
        "stick": 0,
        "stick_id": 0,
        "stick_start_at": 0,
        "stick_expire_at": 0,
        "stick_type": 0,
        "feed_source": "",
        "article": {
            "id": 156261927,
            "mask_id": "1zsabeyu",
            "uri": "meipian:\/\/article\/detail?__experimentIds__=&__feedType__=400014&__flush_num__=0&__locationId__=16&__path__=tag3&__trackId__=14b851ac93b322d0&mask_id=1zsabeyu&__showStyle__=3",
            "abstract": "桃花(新韵)七绝桃花又扮窗前景，恰遇春风迷经庭。滿树芳菲轻雨润，香魂缕缕醉心晴。春(新韵)(尘封的记",
            "title": "写在春天",
            "addition_user_id": 0,
            "addition": "",
            "addition_uri": "",
            "visit_count": 2843,
            "praise_count": 913,
            "image_count": 11,
            "comment_count": 338,
            "cover_imgs": ["http:\/\/static2.ivwen.com\/users\/7400503\/47048e4ca30742fda6a026d043043085.jpg", "http:\/\/static2.ivwen.com\/users\/7400503\/2d32f861c427478599782b13299177e7.jpg", "http:\/\/static2.ivwen.com\/users\/7400503\/31b522f11ed54978a4c99ca1d034d78a.jpg"],
            "feed_tag_info": {
                "tag_name": "我的原创诗",
                "uri": "meipian:\/\/activity\/detail?__experimentIds__=&__feedType__=400014&__flush_num__=0&__locationId__=16&__maskId__=1zsabeyu&__path__=tag3&__trackId__=14b851ac93b322d0&topic_id=52"
            },
            "addition_tag_info": {
                "tag_id": 0,
                "tag_name": "",
                "img_url": ""
            }
        },
        "video": {},
        "event": [],
        "author": {
            "id": 7400503,
            "uri": "meipian:\/\/user\/column?__experimentIds__=&__feedType__=400014&__flush_num__=0&__locationId__=16&__path__=tag3&__trackId__=14b851ac93b322d0&author_id=7400503",
            "is_official": 0,
            "nickname": "尘封的记忆",
            "head_img": "https:\/\/ss2.meipian.me\/users\/7400503\/915b2766042f46f7a87ddf0a34f5387b.jpg",
            "bedge_img": "",
            "label_img": "",
            "tag_img": ""
        },
        "source": {
            "source": "feedV4"
        },
        "feed_type": 400014,
        "style": 3,
        "item_type": 1,
        "uninterest_option": [{
            "type": 1,
            "name": "不喜欢这篇文章",
            "target_id": "156261927"
        }, {
            "type": 2,
            "name": "不喜欢这个作者",
            "target_id": "7400503"
        }, {
            "type": 7,
            "name": "不喜欢这类文章",
            "target_id": ""
        }]
    }, {
        "type": 1,
        "list_id": "1|133480493",
        "stick": 0,
        "stick_id": 0,
        "stick_start_at": 0,
        "stick_expire_at": 0,
        "stick_type": 0,
        "feed_source": "",
        "article": {
            "id": 133480493,
            "mask_id": "1pbiu864",
            "uri": "meipian:\/\/article\/detail?__experimentIds__=&__feedType__=400014&__flush_num__=0&__locationId__=17&__path__=tag3&__trackId__=14b851ac93b322d0&mask_id=1pbiu864&__showStyle__=3",
            "abstract": "作者\/王志山图片\/网络老山人的夜晚\n后半夜深山茅屋老山人的呼噜声有很强的韵律感觉，是森林音乐活了四五",
            "title": "写给祖国的情诗",
            "addition_user_id": 0,
            "addition": "",
            "addition_uri": "",
            "visit_count": 1186,
            "praise_count": 95,
            "image_count": 15,
            "comment_count": 20,
            "cover_imgs": ["http:\/\/static2.ivwen.com\/users\/5791861\/a1b829d1685286f54702d5f2ceb915a9.jpg", "http:\/\/static2.ivwen.com\/users\/5791861\/96527724d6904869a57b3ca6489df0b4.jpg", "http:\/\/static2.ivwen.com\/users\/5791861\/aae5e0a60f8c40e9b7f5d0f702b61bca.jpg"],
            "feed_tag_info": {
                "tag_name": "我的原创诗",
                "uri": "meipian:\/\/activity\/detail?__experimentIds__=&__feedType__=400014&__flush_num__=0&__locationId__=17&__maskId__=1pbiu864&__path__=tag3&__trackId__=14b851ac93b322d0&topic_id=52"
            },
            "addition_tag_info": {
                "tag_id": 0,
                "tag_name": "",
                "img_url": ""
            }
        },
        "video": {},
        "event": [],
        "author": {
            "id": 5791861,
            "uri": "meipian:\/\/user\/column?__experimentIds__=&__feedType__=400014&__flush_num__=0&__locationId__=17&__path__=tag3&__trackId__=14b851ac93b322d0&author_id=5791861",
            "is_official": 0,
            "nickname": "思*美篇原创",
            "head_img": "http:\/\/static2.ivwen.com\/users\/5791861\/1803ee17e0be4b2d95e14013a2f14e97.jpg?meipian\/bucket\/ivwen\/key\/dXNlcnMvNTc5MTg2MS8xODAzZWUxN2UwYmU0YjJkOTVlMTQwMTNhMmYxNGU5Ny5qcGc=\/sign\/78b699c09678cacee5010d104eb626b4",
            "bedge_img": "https:\/\/ss2.meipian.me\/app\/vip.png",
            "label_img": "https:\/\/ss2.meipian.me\/app\/label\/sign_mark2.png",
            "tag_img": ""
        },
        "source": {
            "source": "feedV4"
        },
        "feed_type": 400014,
        "style": 3,
        "item_type": 1,
        "uninterest_option": [{
            "type": 1,
            "name": "不喜欢这篇文章",
            "target_id": "133480493"
        }, {
            "type": 2,
            "name": "不喜欢这个作者",
            "target_id": "5791861"
        }, {
            "type": 7,
            "name": "不喜欢这类文章",
            "target_id": ""
        }]
    }, {
        "type": 1,
        "list_id": "1|214217034",
        "stick": 0,
        "stick_id": 0,
        "stick_start_at": 0,
        "stick_expire_at": 0,
        "stick_type": 0,
        "feed_source": "",
        "article": {
            "id": 214217034,
            "mask_id": "2qerahdx",
            "uri": "meipian:\/\/article\/detail?__experimentIds__=&__feedType__=400014&__flush_num__=0&__locationId__=18&__path__=tag3&__trackId__=14b851ac93b322d0&mask_id=2qerahdx&__showStyle__=2",
            "abstract": "诗歌是什么你是我灵魂深处的样子当我饥渴劳累困扰时我永远能看到你的光亮你指引我叩开心灵的门窗你让我卸下",
            "title": "诗歌是我灵魂深处的样子",
            "addition_user_id": 0,
            "addition": "",
            "addition_uri": "",
            "visit_count": 203,
            "praise_count": 81,
            "image_count": 7,
            "comment_count": 52,
            "cover_imgs": ["https:\/\/static2.ivwen.com\/users\/16533070\/24033bab59454a98869f83b7659b5767.jpeg?imageMogr2\/crop\/!640x360a0a8", "https:\/\/static2.ivwen.com\/users\/16533070\/1c9b29270be44e9e9b7b4dc8914d2edd.jpeg?imageMogr2\/crop\/!640x360a0a0", "https:\/\/static2.ivwen.com\/users\/16533070\/7062b985946241b98c3ca32b1ca20210.jpeg?imageMogr2\/crop\/!640x360a0a33"],
            "feed_tag_info": {
                "tag_name": "我的原创诗",
                "uri": "meipian:\/\/activity\/detail?__experimentIds__=&__feedType__=400014&__flush_num__=0&__locationId__=18&__maskId__=2qerahdx&__path__=tag3&__trackId__=14b851ac93b322d0&topic_id=52"
            },
            "addition_tag_info": {
                "tag_id": 0,
                "tag_name": "",
                "img_url": ""
            }
        },
        "video": {},
        "event": [],
        "author": {
            "id": 16533070,
            "uri": "meipian:\/\/user\/column?__experimentIds__=&__feedType__=400014&__flush_num__=0&__locationId__=18&__path__=tag3&__trackId__=14b851ac93b322d0&author_id=16533070",
            "is_official": 0,
            "nickname": "心若芷萱",
            "head_img": "https:\/\/ss2.meipian.me\/users\/16533070\/1f268758-4ebe-46a3-9f53-47d578abe5a8.jpg",
            "bedge_img": "",
            "label_img": "",
            "tag_img": ""
        },
        "source": {
            "source": "feedV4"
        },
        "feed_type": 400014,
        "style": 2,
        "item_type": 1,
        "uninterest_option": [{
            "type": 1,
            "name": "不喜欢这篇文章",
            "target_id": "214217034"
        }, {
            "type": 2,
            "name": "不喜欢这个作者",
            "target_id": "16533070"
        }, {
            "type": 7,
            "name": "不喜欢这类文章",
            "target_id": ""
        }]
    }],
    "code": 1000
}
