{
    "data": {
        "articles": [],
        "rcmd_type": "famous_user",
        "interest_user_index": 1,
        "rand_size": 0,
        "interest_users": [{
            "id": 2502390,
            "famous_type": 0,
            "member_type": 0,
            "signature": "人生无根蒂，飘若陌上尘。",
            "rcmd_type": 0,
            "fans_count": 18523,
            "name": "陌上尘",
            "relationship": null,
            "head_img": "http:\/\/static2.ivwen.com\/users\/2502390\/5ca67c92597c4efd9e0d9a1f0cb50525.jpg",
            "bedge_img": "",
            "label_img": "",
            "uri": "meipian:\/\/user\/column?author_id=2502390&__path__=follow",
            "summary_tips": "22 文章 · 18523 粉丝",
            "member_status": 0,
            "member_icon": ""
        }, {
            "id": 908914,
            "famous_type": 0,
            "member_type": 0,
            "signature": "美篇，我们共同的成长经历和美好记忆！",
            "rcmd_type": 0,
            "fans_count": 23297,
            "name": "归海爵明",
            "relationship": null,
            "head_img": "http:\/\/static2.ivwen.com\/users\/908914\/a16097f355ad41dfa13a77b6b3c68531.jpg",
            "bedge_img": "",
            "label_img": "",
            "uri": "meipian:\/\/user\/column?author_id=908914&__path__=follow",
            "summary_tips": "48 文章 · 23297 粉丝",
            "member_status": 0,
            "member_icon": ""
        }, {
            "id": 672657,
            "famous_type": 0,
            "member_type": 0,
            "signature": "黑夜给了我一双黑色的眼睛，我却用他寻找光明。顾城诗",
            "rcmd_type": 0,
            "fans_count": 24281,
            "name": "何辉",
            "relationship": null,
            "head_img": "https:\/\/ss2.meipian.me\/users\/672657\/4728e2dd5cda6cae272b82dfccd3d03f",
            "bedge_img": "",
            "label_img": "",
            "uri": "meipian:\/\/user\/column?author_id=672657&__path__=follow",
            "summary_tips": "45 文章 · 24281 粉丝",
            "member_status": 0,
            "member_icon": ""
        }, {
            "id": 692093,
            "famous_type": 0,
            "member_type": 0,
            "signature": "心有多开放，世界就有多精彩！",
            "rcmd_type": 0,
            "fans_count": 20632,
            "name": "随风",
            "relationship": null,
            "head_img": "http:\/\/static2.ivwen.com\/users\/692093\/bbe3398167b2401eba093dd942c8db15.jpg",
            "bedge_img": "",
            "label_img": "",
            "uri": "meipian:\/\/user\/column?author_id=692093&__path__=follow",
            "summary_tips": "39 文章 · 20632 粉丝",
            "member_status": 0,
            "member_icon": ""
        }, {
            "id": 440772,
            "famous_type": 2,
            "member_type": 0,
            "signature": "jonzzz.com • 不为摄影 • 只为旅行",
            "rcmd_type": 0,
            "fans_count": 31369,
            "name": "北京张子",
            "relationship": null,
            "head_img": "http:\/\/static2.ivwen.com\/users\/440772\/7a829329d82944cb836fb6783fea337c.jpg",
            "bedge_img": "https:\/\/ss2.meipian.me\/app\/vip.png",
            "label_img": "https:\/\/ss2.meipian.me\/app\/label\/sign_mark2.png",
            "uri": "meipian:\/\/user\/column?author_id=440772&__path__=follow",
            "summary_tips": "24 文章 · 31369 粉丝",
            "member_status": 0,
            "member_icon": ""
        }, {
            "id": 9894382,
            "famous_type": 0,
            "member_type": 0,
            "signature": "感受生活，享受生活",
            "rcmd_type": 0,
            "fans_count": 18250,
            "name": "红梅",
            "relationship": null,
            "head_img": "http:\/\/static2.ivwen.com\/users\/9894382\/64f5e18446ad43009291105958a86d3b.jpg",
            "bedge_img": "",
            "label_img": "",
            "uri": "meipian:\/\/user\/column?author_id=9894382&__path__=follow",
            "summary_tips": "15 文章 · 18250 粉丝",
            "member_status": 0,
            "member_icon": ""
        }, {
            "id": 10002,
            "famous_type": 0,
            "member_type": 3,
            "signature": "美篇编辑组最后的清流",
            "rcmd_type": 0,
            "fans_count": 50225,
            "name": "青锋",
            "relationship": null,
            "head_img": "http:\/\/static2.ivwen.com\/users\/10002\/b62d7b156e77443991a05c578025ccc7.jpg",
            "bedge_img": "https:\/\/static2.ivwen.com\/app\/bedge\/enterprise.png",
            "label_img": "",
            "uri": "meipian:\/\/user\/column?author_id=10002&__path__=follow",
            "summary_tips": "89 文章 · 50225 粉丝",
            "member_status": 0,
            "member_icon": ""
        }, {
            "id": 641859,
            "famous_type": 2,
            "member_type": 0,
            "signature": "它将在幽暗中走着，充满了温柔，在披花的路上。",
            "rcmd_type": 0,
            "fans_count": 31182,
            "name": "青天驴子",
            "relationship": null,
            "head_img": "http:\/\/static2.ivwen.com\/users\/641859\/a5f7ec6fcf954e4b9323171021ecf71f.jpg",
            "bedge_img": "https:\/\/ss2.meipian.me\/app\/vip.png",
            "label_img": "https:\/\/ss2.meipian.me\/app\/label\/sign_mark2.png",
            "uri": "meipian:\/\/user\/column?author_id=641859&__path__=follow",
            "summary_tips": "61 文章 · 31182 粉丝",
            "member_status": 0,
            "member_icon": ""
        }, {
            "id": 733406,
            "famous_type": 0,
            "member_type": 0,
            "signature": "寂默的天空，一只会飞的鱼...",
            "rcmd_type": 0,
            "fans_count": 16980,
            "name": "默",
            "relationship": null,
            "head_img": "http:\/\/static2.ivwen.com\/users\/733406\/e493c9975702402897d17788b8841272.jpg",
            "bedge_img": "",
            "label_img": "",
            "uri": "meipian:\/\/user\/column?author_id=733406&__path__=follow",
            "summary_tips": "34 文章 · 16980 粉丝",
            "member_status": 0,
            "member_icon": ""
        }, {
            "id": 496180,
            "famous_type": 0,
            "member_type": 0,
            "signature": "也许是一切，也许什么也不是……",
            "rcmd_type": 0,
            "fans_count": 27843,
            "name": "红色跑车",
            "relationship": null,
            "head_img": "http:\/\/static2.ivwen.com\/users\/496180\/45481465de1a4b018e800085e4147b9c.jpg",
            "bedge_img": "",
            "label_img": "",
            "uri": "meipian:\/\/user\/column?author_id=496180&__path__=follow",
            "summary_tips": "113 文章 · 27843 粉丝",
            "member_status": 1,
            "member_icon": ""
        }, {
            "id": 1778690,
            "famous_type": 0,
            "member_type": 0,
            "signature": "吃更多好吃的，玩更多好玩的！",
            "rcmd_type": 0,
            "fans_count": 14738,
            "name": "楚_Luisa",
            "relationship": null,
            "head_img": "http:\/\/static2.ivwen.com\/users\/1778690\/dba557f8966845e7997714c45e2f3f4b.jpg",
            "bedge_img": "",
            "label_img": "",
            "uri": "meipian:\/\/user\/column?author_id=1778690&__path__=follow",
            "summary_tips": "10 文章 · 14738 粉丝",
            "member_status": 0,
            "member_icon": ""
        }, {
            "id": 735022,
            "famous_type": 2,
            "member_type": 0,
            "signature": "胡同大爷挺爱得瑟的",
            "rcmd_type": 0,
            "fans_count": 23665,
            "name": "司马南",
            "relationship": null,
            "head_img": "http:\/\/static2.ivwen.com\/users\/735022\/2c38d953838448d2a88be8a5a9d1a3e5.jpg",
            "bedge_img": "https:\/\/ss2.meipian.me\/app\/vip.png",
            "label_img": "https:\/\/ss2.meipian.me\/app\/label\/sign_mark2.png",
            "uri": "meipian:\/\/user\/column?author_id=735022&__path__=follow",
            "summary_tips": "268 文章 · 23665 粉丝",
            "member_status": 2,
            "member_icon": "https:\/\/static2.ivwen.com\/app\/member_label@3x.png"
        }, {
            "id": 1034,
            "famous_type": 2,
            "member_type": 0,
            "signature": "汤人仁",
            "rcmd_type": 0,
            "fans_count": 32941,
            "name": "汤人仁",
            "relationship": null,
            "head_img": "http:\/\/static2.ivwen.com\/users\/1034\/e547fde7dee14d2a801f7825224d0f12.jpg",
            "bedge_img": "https:\/\/ss2.meipian.me\/app\/vip.png",
            "label_img": "https:\/\/ss2.meipian.me\/app\/label\/sign_mark2.png",
            "uri": "meipian:\/\/user\/column?author_id=1034&__path__=follow",
            "summary_tips": "85 文章 · 32941 粉丝",
            "member_status": 2,
            "member_icon": "https:\/\/static2.ivwen.com\/app\/member_label@3x.png"
        }, {
            "id": 306315,
            "famous_type": 2,
            "member_type": 0,
            "signature": "梦想在指尖自由飞翔……",
            "rcmd_type": 0,
            "fans_count": 46103,
            "name": "女画家-陶云峰",
            "relationship": null,
            "head_img": "http:\/\/static2.ivwen.com\/users\/306315\/e5eed9fdecea483c86a5ffa9f259f25b.jpg",
            "bedge_img": "https:\/\/ss2.meipian.me\/app\/vip.png",
            "label_img": "https:\/\/ss2.meipian.me\/app\/label\/sign_mark2.png",
            "uri": "meipian:\/\/user\/column?author_id=306315&__path__=follow",
            "summary_tips": "70 文章 · 46103 粉丝",
            "member_status": 0,
            "member_icon": ""
        }, {
            "id": 12214731,
            "famous_type": 2,
            "member_type": 0,
            "signature": "不再问彼岸在哪里！",
            "rcmd_type": 0,
            "fans_count": 39640,
            "name": "阳光中的谜",
            "relationship": null,
            "head_img": "http:\/\/static2.ivwen.com\/users\/12214731\/2ea9487d4ccf4560a6d707ad374eb7aa.jpg",
            "bedge_img": "https:\/\/ss2.meipian.me\/app\/vip.png",
            "label_img": "https:\/\/ss2.meipian.me\/app\/label\/sign_mark2.png",
            "uri": "meipian:\/\/user\/column?author_id=12214731&__path__=follow",
            "summary_tips": "134 文章 · 39640 粉丝",
            "member_status": 0,
            "member_icon": ""
        }, {
            "id": 1274915,
            "famous_type": 2,
            "member_type": 0,
            "signature": "此生半路而來，誰知寂寞如斯",
            "rcmd_type": 0,
            "fans_count": 29722,
            "name": "莫箬Merro",
            "relationship": null,
            "head_img": "https:\/\/ss2.meipian.me\/users\/1274915\/7751b333bb394fa49438f4e74a6cd4ca.jpg",
            "bedge_img": "https:\/\/ss2.meipian.me\/app\/vip.png",
            "label_img": "https:\/\/ss2.meipian.me\/app\/label\/sign_mark2.png",
            "uri": "meipian:\/\/user\/column?author_id=1274915&__path__=follow",
            "summary_tips": "30 文章 · 29722 粉丝",
            "member_status": 0,
            "member_icon": ""
        }, {
            "id": 1741461,
            "famous_type": 0,
            "member_type": 0,
            "signature": "青山在远",
            "rcmd_type": 0,
            "fans_count": 17741,
            "name": "Mac Y",
            "relationship": null,
            "head_img": "http:\/\/static2.ivwen.com\/users\/1741461\/f04668c25814404bad6ad23444c66876.jpg",
            "bedge_img": "",
            "label_img": "",
            "uri": "meipian:\/\/user\/column?author_id=1741461&__path__=follow",
            "summary_tips": "11 文章 · 17741 粉丝",
            "member_status": 0,
            "member_icon": ""
        }, {
            "id": 318589,
            "famous_type": 2,
            "member_type": 0,
            "signature": "心无尘，淡若水，安静，做好自己！",
            "rcmd_type": 0,
            "fans_count": 47617,
            "name": "江南雨 ☔️",
            "relationship": null,
            "head_img": "http:\/\/static2.ivwen.com\/users\/318589\/1600c54a057447b694f2a8ea5b0bd89e.jpg",
            "bedge_img": "https:\/\/ss2.meipian.me\/app\/vip.png",
            "label_img": "https:\/\/ss2.meipian.me\/app\/label\/sign_mark2.png",
            "uri": "meipian:\/\/user\/column?author_id=318589&__path__=follow",
            "summary_tips": "41 文章 · 47617 粉丝",
            "member_status": 0,
            "member_icon": ""
        }, {
            "id": 872937,
            "famous_type": 0,
            "member_type": 0,
            "signature": "自然，随性，“好色”大都体现在与吃喝有关与花草有关…",
            "rcmd_type": 0,
            "fans_count": 21484,
            "name": "KOKU",
            "relationship": null,
            "head_img": "http:\/\/static2.ivwen.com\/users\/872937\/7e77c287209b47a6929ef7518cbbb58a.jpg",
            "bedge_img": "",
            "label_img": "",
            "uri": "meipian:\/\/user\/column?author_id=872937&__path__=follow",
            "summary_tips": "30 文章 · 21484 粉丝",
            "member_status": 0,
            "member_icon": ""
        }, {
            "id": 1025237,
            "famous_type": 0,
            "member_type": 0,
            "signature": "微信号可约拍:smallwestwest，交流勿扰",
            "rcmd_type": 0,
            "fans_count": 22515,
            "name": "陈希远",
            "relationship": null,
            "head_img": "http:\/\/static2.ivwen.com\/users\/1025237\/66013092d29043e190a2aa9af0680054.jpg",
            "bedge_img": "",
            "label_img": "",
            "uri": "meipian:\/\/user\/column?author_id=1025237&__path__=follow",
            "summary_tips": "24 文章 · 22515 粉丝",
            "member_status": 0,
            "member_icon": ""
        }],
        "rcmd_total": 0,
        "has_follow": 0,
        "find_more": {
            "title": "发现更多感兴趣的人",
            "images": ["https:\/\/ss2.meipian.me\/config\/recommend\/icon\/look_friend_1.png", "https:\/\/ss2.meipian.me\/config\/recommend\/icon\/look_friend_2.png", "https:\/\/ss2.meipian.me\/config\/recommend\/icon\/look_friend_3.png", "https:\/\/ss2.meipian.me\/config\/recommend\/icon\/look_friend_4.png"]
        }
    },
    "code": 1000
}
