{
    "data": [{
        "id": 33849,
        "list_id": 33849,
        "user": {
            "id": 3700795,
            "uri": "meipian:\/\/user\/column?author_id=3700795&__path__=circle_talk_list",
            "nickname": "春暖花开",
            "head_img": "http:\/\/static2.ivwen.com\/users\/3700795\/f6796eff924d469784e3a6b79a51cda8.jpg"
        },
        "talk": {
            "id": 2529847,
            "text": "清明节必读的十首经典诗词，不能只会“清明时节雨纷纷”！清明节又叫踏青节，在仲春与暮春之交，也就是冬至后的第108天，是中国传统节日之一，也是最重要的祭祀节日之一，是祭祖和扫墓的日子。经国务院批准，",
            "visit_count": 446,
            "comment_count": 26,
            "praise_count": 57,
            "summary": "%d 阅读  %d 评论  %d 点赞",
            "img": "http:\/\/static2.ivwen.com\/users\/3700795\/293a700511cbcf144b7f4cdc5431448a.gif-cover2",
            "create_time": 1586069625,
            "display_time": "04-05"
        }
    }, {
        "id": 33848,
        "list_id": 33848,
        "user": {
            "id": 35414130,
            "uri": "meipian:\/\/user\/column?author_id=35414130&__path__=circle_talk_list",
            "nickname": "逸帆风顺",
            "head_img": "http:\/\/thirdwx.qlogo.cn\/mmopen\/vi_32\/Q0j4TwGTfTJZIAnFRA5zvdXuGibMiaEMK693mQnKUZCMu9w1Z0BS54s7ZJCkD5eJiaf8micwAngwOIYviajX8JPO4PA\/132"
        },
        "talk": {
            "id": 2529901,
            "text": "年”字最早的写法是一个人背负成熟的禾的形象，表示庄稼成熟，即“年成”。古时候所谓的“年成”指的就是这个。因此古代的字书把“年”字放禾部。由于谷禾一般都是一岁一熟，所以“年”与岁在日期数量上有相同周期了",
            "visit_count": 162,
            "comment_count": 4,
            "praise_count": 30,
            "summary": "%d 阅读  %d 评论  %d 点赞",
            "img": "http:\/\/static2.ivwen.com\/users\/35414130\/0102ccecc1617a6882d4faff3961d70b.jpg-cover2",
            "create_time": 1586071367,
            "display_time": "04-05"
        }
    }, {
        "id": 33847,
        "list_id": 33847,
        "user": {
            "id": 45157496,
            "uri": "meipian:\/\/user\/column?author_id=45157496&__path__=circle_talk_list",
            "nickname": "漠克",
            "head_img": "https:\/\/ss2.meipian.me\/users\/45157496\/8d991baa0d3748d88636c3a4d42fa506.jpg"
        },
        "talk": {
            "id": 2530002,
            "text": "临张迁碑",
            "visit_count": 135,
            "comment_count": 10,
            "praise_count": 30,
            "summary": "%d 阅读  %d 评论  %d 点赞",
            "img": "http:\/\/static2.ivwen.com\/users\/45157496\/131551e3e92010e518ccd1a5cc8e5cbf.jpg-cover2",
            "create_time": 1586074978,
            "display_time": "04-05"
        }
    }, {
        "id": 33846,
        "list_id": 33846,
        "user": {
            "id": 40224467,
            "uri": "meipian:\/\/user\/column?author_id=40224467&__path__=circle_talk_list",
            "nickname": "若水",
            "head_img": "http:\/\/static2.ivwen.com\/users\/40224467\/0b0b296b196a4f19a6d840a45b992226.jpg"
        },
        "talk": {
            "id": 2530070,
            "text": "你总有一天要跟所以的记忆相安无事握手言和，那里面有她也有你，有她的青春也有你的年华。那个人永远活在时间里了，你把她拉不出来，自己也回不去。就这样吧！让她安静的留在那里。她不",
            "visit_count": 256,
            "comment_count": 15,
            "praise_count": 54,
            "summary": "%d 阅读  %d 评论  %d 点赞",
            "img": "http:\/\/static2.ivwen.com\/users\/40224467\/56af923f20d047bb0f947b0736eba5eb.jpg-cover2",
            "create_time": 1586076586,
            "display_time": "04-05"
        }
    }, {
        "id": 33845,
        "list_id": 33845,
        "user": {
            "id": 5446644,
            "uri": "meipian:\/\/user\/column?author_id=5446644&__path__=circle_talk_list",
            "nickname": "祥子",
            "head_img": "https:\/\/ss2.meipian.me\/users\/5446644\/93a5b0849c6b4784ad86aac87cacfc85.jpg"
        },
        "talk": {
            "id": 2530140,
            "text": "“风景清明后，云山睥睨前。”穿越寒冬，大地回春，万物复苏，神州大地已是一片生机。凶猛的疫病没有击垮我们，正如数千年来，无数磨难从未压垮我们这个民族的脊梁。中国共产党是带领中华民族从灾难中奋起的力量之源",
            "visit_count": 194,
            "comment_count": 7,
            "praise_count": 37,
            "summary": "%d 阅读  %d 评论  %d 点赞",
            "img": "http:\/\/static2.ivwen.com\/users\/5446644\/48783e0a3fcff0f4f594b1d81d91e637.jpg-cover2",
            "create_time": 1586078024,
            "display_time": "04-05"
        }
    }, {
        "id": 33844,
        "list_id": 33844,
        "user": {
            "id": 120199229,
            "uri": "meipian:\/\/user\/column?author_id=120199229&__path__=circle_talk_list",
            "nickname": "孤独缠身",
            "head_img": "https:\/\/ss2.meipian.me\/users\/120199229\/951a0c5b7e6cc937534fd6220e572690"
        },
        "talk": {
            "id": 2530160,
            "text": "了解清明节清明节，又称踏青节、行清节、三月节、祭祖节，是冬至后的第108天，节期在仲春与暮春之交。清明节是传统的重大春祭节日。人间四月芳菲始，又是一年清明时。二十四节气之一的“清明”就要来到了。",
            "visit_count": 295,
            "comment_count": 3,
            "praise_count": 36,
            "summary": "%d 阅读  %d 评论  %d 点赞",
            "img": "http:\/\/static2.ivwen.com\/users\/120199229\/b5819b3f4b44ee7e60c700e1895d89e3.jpg-cover2",
            "create_time": 1586078339,
            "display_time": "04-05"
        }
    }, {
        "id": 33843,
        "list_id": 33843,
        "user": {
            "id": 14307692,
            "uri": "meipian:\/\/user\/column?author_id=14307692&__path__=circle_talk_list",
            "nickname": "香音未改*王德香",
            "head_img": "http:\/\/static2.ivwen.com\/users\/14307692\/ae0257a5094f440eaa1fa09134a8a18b.jpg"
        },
        "talk": {
            "id": 2530174,
            "text": "爱这人间四月，爱这暖暖红尘四月，和草木在一起，向暖而生。置身于春的怀抱，像个孩子一样去寻找，草有新色，花有清香，心有向往，一切皆是欣欣向荣的模样。走过阴霾，沐浴晴朗，经历离别，迎接重逢，珍",
            "visit_count": 459,
            "comment_count": 28,
            "praise_count": 61,
            "summary": "%d 阅读  %d 评论  %d 点赞",
            "img": "http:\/\/static2.ivwen.com\/users\/14307692\/12ad5c0c47d8408aa2bf006dacdd4945.jpg-cover2",
            "create_time": 1586078489,
            "display_time": "04-05"
        }
    }, {
        "id": 33842,
        "list_id": 33842,
        "user": {
            "id": 9912924,
            "uri": "meipian:\/\/user\/column?author_id=9912924&__path__=circle_talk_list",
            "nickname": "牛牛",
            "head_img": "http:\/\/static2.ivwen.com\/users\/9912924\/9a6eb9d720f740068618da85d4419cf0.jpg"
        },
        "talk": {
            "id": 2530178,
            "text": "扁竹兰",
            "visit_count": 231,
            "comment_count": 24,
            "praise_count": 48,
            "summary": "%d 阅读  %d 评论  %d 点赞",
            "img": "http:\/\/static2.ivwen.com\/users\/9912924\/ef27b79c2faf21a34d45a4e5765f9fd3.jpg-cover2",
            "create_time": 1586078514,
            "display_time": "04-05"
        }
    }],
    "code": 1000
}
